OnlySnarf/__init__.py
OnlySnarf/__main__.py
OnlySnarf/snarf.py
OnlySnarf/classes/__init__.py
OnlySnarf/classes/discount.py
OnlySnarf/classes/file.py
OnlySnarf/classes/message.py
OnlySnarf/classes/poll.py
OnlySnarf/classes/profile.py
OnlySnarf/classes/promotion.py
OnlySnarf/classes/schedule.py
OnlySnarf/classes/user.py
OnlySnarf/conf/args-config.conf
OnlySnarf/conf/config.conf
OnlySnarf/conf/onlysnarf_api.service
OnlySnarf/conf/test-config.conf
OnlySnarf/lib/__init__.py
OnlySnarf/lib/api.py
OnlySnarf/lib/config.py
OnlySnarf/lib/driver.py
OnlySnarf/lib/ffmpeg.py
OnlySnarf/lib/menu.py
OnlySnarf/lib/watchdogger.py
OnlySnarf/lib/webdriver/__init__.py
OnlySnarf/lib/webdriver/browser.py
OnlySnarf/lib/webdriver/chat.py
OnlySnarf/lib/webdriver/clear.py
OnlySnarf/lib/webdriver/collections.py
OnlySnarf/lib/webdriver/cookies.py
OnlySnarf/lib/webdriver/discount.py
OnlySnarf/lib/webdriver/download.py
OnlySnarf/lib/webdriver/element.py
OnlySnarf/lib/webdriver/errors.py
OnlySnarf/lib/webdriver/expiration.py
OnlySnarf/lib/webdriver/goto.py
OnlySnarf/lib/webdriver/list.py
OnlySnarf/lib/webdriver/login.py
OnlySnarf/lib/webdriver/message.py
OnlySnarf/lib/webdriver/poll.py
OnlySnarf/lib/webdriver/post.py
OnlySnarf/lib/webdriver/promotion.py
OnlySnarf/lib/webdriver/schedule.py
OnlySnarf/lib/webdriver/settings.py
OnlySnarf/lib/webdriver/upload.py
OnlySnarf/lib/webdriver/users.py
OnlySnarf/lib/webdriver/util.py
OnlySnarf/util/__init__.py
OnlySnarf/util/args.py
OnlySnarf/util/colorize.py
OnlySnarf/util/config.py
OnlySnarf/util/data.py
OnlySnarf/util/defaults.py
OnlySnarf/util/extras.py
OnlySnarf/util/logger.py
OnlySnarf/util/optional_args.py
OnlySnarf/util/urls.py
OnlySnarf/util/user_config.py
OnlySnarf/util/validators.py
OnlySnarf-4.7.2.dist-info/LICENSE.txt
OnlySnarf-4.7.2.dist-info/METADATA
OnlySnarf-4.7.2.dist-info/WHEEL
OnlySnarf-4.7.2.dist-info/entry_points.txt
OnlySnarf-4.7.2.dist-info/top_level.txt
OnlySnarf-4.7.2.dist-info/RECORD
