Metadata-Version: 2.1
Name: OnlySnarf
Version: 4.7.2
Summary: OnlyFans Content Distribution Tool
Home-page: https://github.com/skeetzo/onlysnarf
Author: Skeetzo
Author-email: WebmasterSkeetzo@gmail.com
Keywords: OnlyFans,OnlySnarf,selenium,snarf
Classifier: Development Status :: 5 - Production/Stable
Classifier: Intended Audience :: End Users/Desktop
Classifier: Topic :: System :: Emulators
Classifier: License :: OSI Approved :: MIT License
Classifier: Programming Language :: Python :: 3.8
Classifier: Operating System :: OS Independent
License-File: LICENSE.txt
Requires-Dist: dropbox
Requires-Dist: ffmpeg
Requires-Dist: inquirer
Requires-Dist: marshmallow
Requires-Dist: wget
Requires-Dist: selenium ==4.8.3
Requires-Dist: webdriver-manager ==4.0.0
Requires-Dist: validators
Requires-Dist: flask
Provides-Extra: dev
Requires-Dist: pytest ; extra == 'dev'
Requires-Dist: flask-unittest ; extra == 'dev'
